badfish/__init__.py
badfish/config.py
badfish/main.py
badfish/helpers/__init__.py
badfish/helpers/async_lru.py
badfish/helpers/exceptions.py
badfish/helpers/http_client.py
badfish/helpers/logger.py
badfish/helpers/parser.py
badfish-1.0.6.dist-info/licenses/LICENSE
badfish-1.0.6.dist-info/METADATA
badfish-1.0.6.dist-info/WHEEL
badfish-1.0.6.dist-info/entry_points.txt
badfish-1.0.6.dist-info/top_level.txt
badfish-1.0.6.dist-info/zip-safe
badfish-1.0.6.dist-info/RECORD
