Metadata-Version: 2.4
Name: badfish
Version: 1.0.6
Summary: Badfish is a Redfish-based API tool for managing bare-metal systems via the Redfish API
Home-page: https://github.com/redhat-performance/badfish
Author: Gonzalo Rafuls
Author-email: gonza@redhat.com
License: GPLv3
Project-URL: Bug Tracker, https://github.com/redhat-performance/badfish/issues
Project-URL: Documentation, https://github.com/redhat-performance/badfish/blob/master/README.md
Project-URL: Source Code, https://github.com/redhat-performance/badfish
Keywords: oob,management
Platform: any
Classifier: Development Status :: 5 - Production/Stable
Classifier: Programming Language :: Python :: 3
Classifier: Operating System :: OS Independent
Classifier: Programming Language :: Python :: 3
Classifier: Programming Language :: Python :: 3.10
Classifier: Programming Language :: Python :: 3.11
Classifier: Programming Language :: Python :: 3.12
Classifier: Programming Language :: Python :: 3.13
Classifier: Programming Language :: Python :: 3.14
Requires-Python: >=3.10
License-File: LICENSE
Requires-Dist: pyyaml>=3.10
Requires-Dist: aiohttp>=3.7.4
Requires-Dist: setuptools>=39.0
Dynamic: license-file
